aliyunsdket_industry_openapi/__init__.py
aliyunsdket_industry_openapi/request/__init__.py
aliyunsdket_industry_openapi/request/v20200824/GetMqttConnectRequest.py
aliyunsdket_industry_openapi/request/v20200824/GetNonceRequest.py
aliyunsdket_industry_openapi/request/v20200824/ListMeasurePointListByNodeCodePageRequest.py
aliyunsdket_industry_openapi/request/v20200824/QueryFieldLatestBySourcePointRequest.py
aliyunsdket_industry_openapi/request/v20200824/QueryIndustryDeviceDataRequest.py
aliyunsdket_industry_openapi/request/v20200824/QueryIndustryDeviceLimitsDataRequest.py
aliyunsdket_industry_openapi/request/v20200824/QueryIndustryDeviceStatusDataRequest.py
aliyunsdket_industry_openapi/request/v20200824/SourcePointBatchRequest.py
aliyunsdket_industry_openapi/request/v20200824/UploadIndustryDeviceDataRequest.py
aliyunsdket_industry_openapi/request/v20200824/__init__.py
aliyun_python_sdk_et_industry_openapi-3.6.dist-info/LICENSE
aliyun_python_sdk_et_industry_openapi-3.6.dist-info/METADATA
aliyun_python_sdk_et_industry_openapi-3.6.dist-info/WHEEL
aliyun_python_sdk_et_industry_openapi-3.6.dist-info/top_level.txt
aliyun_python_sdk_et_industry_openapi-3.6.dist-info/RECORD
